<?xml version="1.0" encoding="utf-8"?>
<TextureAtlas imagePath="Bryce_assets.png">
	<!-- Created with Adobe Animate version 21.0.1.37179 -->
	<!-- http://www.adobe.com/products/animate.html -->
	<SubTexture name="BRYCE IDLE0000" x="10" y="10" width="501" height="939" frameX="-16" frameY="-20" frameWidth="614" frameHeight="959"/>
	<SubTexture name="BRYCE IDLE0001" x="593" y="10" width="519" height="939" frameX="-16" frameY="-20" frameWidth="614" frameHeight="959"/>
	<SubTexture name="BRYCE IDLE0002" x="1194" y="10" width="503" height="955" frameX="-7" frameY="-4" frameWidth="614" frameHeight="959"/>
	<SubTexture name="BRYCE IDLE0003" x="1779" y="10" width="488" height="955" frameX="-7" frameY="-4" frameWidth="614" frameHeight="959"/>
	<SubTexture name="BRYCE IDLE0004" x="2349" y="10" width="497" height="958" frameX="-1" frameY="-1" frameWidth="614" frameHeight="959"/>
	<SubTexture name="BRYCE IDLE0005" x="2928" y="10" width="505" height="958" frameX="-1" frameY="-1" frameWidth="614" frameHeight="959"/>
	<SubTexture name="BRYCE IDLE0006" x="3515" y="10" width="552" height="959" frameX="0" frameY="0" frameWidth="614" frameHeight="959"/>
	<SubTexture name="BRYCE IDLE0007" x="4149" y="10" width="541" height="959" frameX="0" frameY="0" frameWidth="614" frameHeight="959"/>
	<SubTexture name="BRYCE IDLE0008" x="4772" y="10" width="597" height="882" frameX="-17" frameY="-77" frameWidth="614" frameHeight="959"/>
	<SubTexture name="BRYCE IDLE0009" x="4772" y="10" width="597" height="882" frameX="-17" frameY="-77" frameWidth="614" frameHeight="959"/>
	<SubTexture name="BRYCE IDLE0010" x="5451" y="10" width="562" height="917" frameX="-25" frameY="-42" frameWidth="614" frameHeight="959"/>
	<SubTexture name="BRYCE IDLE0011" x="5451" y="10" width="562" height="917" frameX="-25" frameY="-42" frameWidth="614" frameHeight="959"/>
	<SubTexture name="BRYCE IDLE0012" x="6095" y="10" width="563" height="920" frameX="-22" frameY="-39" frameWidth="614" frameHeight="959"/>
	<SubTexture name="BRYCE IDLE0013" x="6740" y="10" width="562" height="918" frameX="-23" frameY="-41" frameWidth="614" frameHeight="959"/>
	<SubTexture name="BRYCE Left0000" x="7384" y="10" width="562" height="911" frameX="0" frameY="0" frameWidth="571" frameHeight="911"/>
	<SubTexture name="BRYCE Left0001" x="7384" y="10" width="562" height="911" frameX="0" frameY="0" frameWidth="571" frameHeight="911"/>
	<SubTexture name="BRYCE Left0002" x="10" y="1051" width="537" height="910" frameX="-34" frameY="-1" frameWidth="571" frameHeight="911"/>
	<SubTexture name="BRYCE Left0003" x="629" y="1051" width="537" height="910" frameX="-34" frameY="-1" frameWidth="571" frameHeight="911"/>
	<SubTexture name="BRYCE Left0004" x="1248" y="1051" width="534" height="910" frameX="-37" frameY="-1" frameWidth="571" frameHeight="911"/>
	<SubTexture name="BRYCE Left0005" x="1248" y="1051" width="534" height="910" frameX="-37" frameY="-1" frameWidth="571" frameHeight="911"/>
	<SubTexture name="BRYCE Left0006" x="1248" y="1051" width="534" height="910" frameX="-37" frameY="-1" frameWidth="571" frameHeight="911"/>
	<SubTexture name="BRYCE Left0007" x="1248" y="1051" width="534" height="910" frameX="-37" frameY="-1" frameWidth="571" frameHeight="911"/>
	<SubTexture name="BRYCE Left0008" x="1248" y="1051" width="534" height="910" frameX="-37" frameY="-1" frameWidth="571" frameHeight="911"/>
	<SubTexture name="BRYCE Left0009" x="1248" y="1051" width="534" height="910" frameX="-37" frameY="-1" frameWidth="571" frameHeight="911"/>
	<SubTexture name="BRYCE Left0010" x="1248" y="1051" width="534" height="910" frameX="-37" frameY="-1" frameWidth="571" frameHeight="911"/>
	<SubTexture name="BRYCE Left0011" x="1248" y="1051" width="534" height="910" frameX="-37" frameY="-1" frameWidth="571" frameHeight="911"/>
	<SubTexture name="BRYCE Left0012" x="1248" y="1051" width="534" height="910" frameX="-37" frameY="-1" frameWidth="571" frameHeight="911"/>
	<SubTexture name="BRYCE Left0013" x="1248" y="1051" width="534" height="910" frameX="-37" frameY="-1" frameWidth="571" frameHeight="911"/>
	<SubTexture name="BRYCE Left0014" x="1248" y="1051" width="534" height="910" frameX="-37" frameY="-1" frameWidth="571" frameHeight="911"/>
	<SubTexture name="BRYCE Left0015" x="1248" y="1051" width="534" height="910" frameX="-37" frameY="-1" frameWidth="571" frameHeight="911"/>
	<SubTexture name="BRYCE Left0016" x="1248" y="1051" width="534" height="910" frameX="-37" frameY="-1" frameWidth="571" frameHeight="911"/>
	<SubTexture name="BRYCE Left0017" x="1248" y="1051" width="534" height="910" frameX="-37" frameY="-1" frameWidth="571" frameHeight="911"/>
	<SubTexture name="BRYCE Left0018" x="1248" y="1051" width="534" height="910" frameX="-37" frameY="-1" frameWidth="571" frameHeight="911"/>
	<SubTexture name="BRYCE Left0019" x="1248" y="1051" width="534" height="910" frameX="-37" frameY="-1" frameWidth="571" frameHeight="911"/>
	<SubTexture name="BRYCE Left0020" x="1248" y="1051" width="534" height="910" frameX="-37" frameY="-1" frameWidth="571" frameHeight="911"/>
	<SubTexture name="BRYCE Left0021" x="1248" y="1051" width="534" height="910" frameX="-37" frameY="-1" frameWidth="571" frameHeight="911"/>
	<SubTexture name="BRYCE Left0022" x="1248" y="1051" width="534" height="910" frameX="-37" frameY="-1" frameWidth="571" frameHeight="911"/>
	<SubTexture name="BRYCE Left0023" x="1248" y="1051" width="534" height="910" frameX="-37" frameY="-1" frameWidth="571" frameHeight="911"/>
	<SubTexture name="BRYCE down0000" x="1864" y="1051" width="578" height="833" frameX="0" frameY="-32" frameWidth="578" frameHeight="865"/>
	<SubTexture name="BRYCE down0001" x="1864" y="1051" width="578" height="833" frameX="0" frameY="-32" frameWidth="578" frameHeight="865"/>
	<SubTexture name="BRYCE down0002" x="2524" y="1051" width="541" height="860" frameX="-5" frameY="-5" frameWidth="578" frameHeight="865"/>
	<SubTexture name="BRYCE down0003" x="3147" y="1051" width="541" height="860" frameX="-5" frameY="-5" frameWidth="578" frameHeight="865"/>
	<SubTexture name="BRYCE down0004" x="3770" y="1051" width="538" height="865" frameX="-5" frameY="0" frameWidth="578" frameHeight="865"/>
	<SubTexture name="BRYCE down0005" x="3770" y="1051" width="538" height="865" frameX="-5" frameY="0" frameWidth="578" frameHeight="865"/>
	<SubTexture name="BRYCE down0006" x="3770" y="1051" width="538" height="865" frameX="-5" frameY="0" frameWidth="578" frameHeight="865"/>
	<SubTexture name="BRYCE down0007" x="3770" y="1051" width="538" height="865" frameX="-5" frameY="0" frameWidth="578" frameHeight="865"/>
	<SubTexture name="BRYCE down0008" x="3770" y="1051" width="538" height="865" frameX="-5" frameY="0" frameWidth="578" frameHeight="865"/>
	<SubTexture name="BRYCE down0009" x="3770" y="1051" width="538" height="865" frameX="-5" frameY="0" frameWidth="578" frameHeight="865"/>
	<SubTexture name="BRYCE down0010" x="3770" y="1051" width="538" height="865" frameX="-5" frameY="0" frameWidth="578" frameHeight="865"/>
	<SubTexture name="BRYCE down0011" x="3770" y="1051" width="538" height="865" frameX="-5" frameY="0" frameWidth="578" frameHeight="865"/>
	<SubTexture name="BRYCE down0012" x="3770" y="1051" width="538" height="865" frameX="-5" frameY="0" frameWidth="578" frameHeight="865"/>
	<SubTexture name="BRYCE down0013" x="3770" y="1051" width="538" height="865" frameX="-5" frameY="0" frameWidth="578" frameHeight="865"/>
	<SubTexture name="BRYCE down0014" x="3770" y="1051" width="538" height="865" frameX="-5" frameY="0" frameWidth="578" frameHeight="865"/>
	<SubTexture name="BRYCE down0015" x="3770" y="1051" width="538" height="865" frameX="-5" frameY="0" frameWidth="578" frameHeight="865"/>
	<SubTexture name="BRYCE down0016" x="3770" y="1051" width="538" height="865" frameX="-5" frameY="0" frameWidth="578" frameHeight="865"/>
	<SubTexture name="BRYCE down0017" x="3770" y="1051" width="538" height="865" frameX="-5" frameY="0" frameWidth="578" frameHeight="865"/>
	<SubTexture name="BRYCE down0018" x="3770" y="1051" width="538" height="865" frameX="-5" frameY="0" frameWidth="578" frameHeight="865"/>
	<SubTexture name="BRYCE down0019" x="3770" y="1051" width="538" height="865" frameX="-5" frameY="0" frameWidth="578" frameHeight="865"/>
	<SubTexture name="BRYCE down0020" x="3770" y="1051" width="538" height="865" frameX="-5" frameY="0" frameWidth="578" frameHeight="865"/>
	<SubTexture name="BRYCE down0021" x="3770" y="1051" width="538" height="865" frameX="-5" frameY="0" frameWidth="578" frameHeight="865"/>
	<SubTexture name="BRYCE down0022" x="3770" y="1051" width="538" height="865" frameX="-5" frameY="0" frameWidth="578" frameHeight="865"/>
	<SubTexture name="BRYCE down0023" x="3770" y="1051" width="538" height="865" frameX="-5" frameY="0" frameWidth="578" frameHeight="865"/>
	<SubTexture name="BRYCE north0000" x="4390" y="1051" width="577" height="970"/>
	<SubTexture name="BRYCE north0001" x="4390" y="1051" width="577" height="970"/>
	<SubTexture name="BRYCE north0002" x="5049" y="1051" width="551" height="940" frameX="-9" frameY="-30" frameWidth="577" frameHeight="970"/>
	<SubTexture name="BRYCE north0003" x="5682" y="1051" width="551" height="940" frameX="-9" frameY="-30" frameWidth="577" frameHeight="970"/>
	<SubTexture name="BRYCE north0004" x="6315" y="1051" width="549" height="937" frameX="-9" frameY="-33" frameWidth="577" frameHeight="970"/>
	<SubTexture name="BRYCE north0005" x="6315" y="1051" width="549" height="937" frameX="-9" frameY="-33" frameWidth="577" frameHeight="970"/>
	<SubTexture name="BRYCE north0006" x="6315" y="1051" width="549" height="937" frameX="-9" frameY="-33" frameWidth="577" frameHeight="970"/>
	<SubTexture name="BRYCE north0007" x="6315" y="1051" width="549" height="937" frameX="-9" frameY="-33" frameWidth="577" frameHeight="970"/>
	<SubTexture name="BRYCE north0008" x="6315" y="1051" width="549" height="937" frameX="-9" frameY="-33" frameWidth="577" frameHeight="970"/>
	<SubTexture name="BRYCE north0009" x="6315" y="1051" width="549" height="937" frameX="-9" frameY="-33" frameWidth="577" frameHeight="970"/>
	<SubTexture name="BRYCE north0010" x="6315" y="1051" width="549" height="937" frameX="-9" frameY="-33" frameWidth="577" frameHeight="970"/>
	<SubTexture name="BRYCE north0011" x="6315" y="1051" width="549" height="937" frameX="-9" frameY="-33" frameWidth="577" frameHeight="970"/>
	<SubTexture name="BRYCE north0012" x="6315" y="1051" width="549" height="937" frameX="-9" frameY="-33" frameWidth="577" frameHeight="970"/>
	<SubTexture name="BRYCE north0013" x="6315" y="1051" width="549" height="937" frameX="-9" frameY="-33" frameWidth="577" frameHeight="970"/>
	<SubTexture name="BRYCE north0014" x="6315" y="1051" width="549" height="937" frameX="-9" frameY="-33" frameWidth="577" frameHeight="970"/>
	<SubTexture name="BRYCE north0015" x="6315" y="1051" width="549" height="937" frameX="-9" frameY="-33" frameWidth="577" frameHeight="970"/>
	<SubTexture name="BRYCE north0016" x="6315" y="1051" width="549" height="937" frameX="-9" frameY="-33" frameWidth="577" frameHeight="970"/>
	<SubTexture name="BRYCE north0017" x="6315" y="1051" width="549" height="937" frameX="-9" frameY="-33" frameWidth="577" frameHeight="970"/>
	<SubTexture name="BRYCE north0018" x="6315" y="1051" width="549" height="937" frameX="-9" frameY="-33" frameWidth="577" frameHeight="970"/>
	<SubTexture name="BRYCE north0019" x="6315" y="1051" width="549" height="937" frameX="-9" frameY="-33" frameWidth="577" frameHeight="970"/>
	<SubTexture name="BRYCE north0020" x="6315" y="1051" width="549" height="937" frameX="-9" frameY="-33" frameWidth="577" frameHeight="970"/>
	<SubTexture name="BRYCE north0021" x="6315" y="1051" width="549" height="937" frameX="-9" frameY="-33" frameWidth="577" frameHeight="970"/>
	<SubTexture name="BRYCE north0022" x="6315" y="1051" width="549" height="937" frameX="-9" frameY="-33" frameWidth="577" frameHeight="970"/>
	<SubTexture name="BRYCE north0023" x="6315" y="1051" width="549" height="937" frameX="-9" frameY="-33" frameWidth="577" frameHeight="970"/>
	<SubTexture name="BRYCE right0000" x="6946" y="1051" width="736" height="796"/>
	<SubTexture name="BRYCE right0001" x="6946" y="1051" width="736" height="796"/>
	<SubTexture name="BRYCE right0002" x="10" y="2103" width="721" height="795" frameX="-3" frameY="-1" frameWidth="736" frameHeight="796"/>
	<SubTexture name="BRYCE right0003" x="813" y="2103" width="721" height="795" frameX="-3" frameY="-1" frameWidth="736" frameHeight="796"/>
	<SubTexture name="BRYCE right0004" x="1616" y="2103" width="718" height="795" frameX="-4" frameY="-1" frameWidth="736" frameHeight="796"/>
	<SubTexture name="BRYCE right0005" x="1616" y="2103" width="718" height="795" frameX="-4" frameY="-1" frameWidth="736" frameHeight="796"/>
	<SubTexture name="BRYCE right0006" x="1616" y="2103" width="718" height="795" frameX="-4" frameY="-1" frameWidth="736" frameHeight="796"/>
	<SubTexture name="BRYCE right0007" x="1616" y="2103" width="718" height="795" frameX="-4" frameY="-1" frameWidth="736" frameHeight="796"/>
	<SubTexture name="BRYCE right0008" x="1616" y="2103" width="718" height="795" frameX="-4" frameY="-1" frameWidth="736" frameHeight="796"/>
	<SubTexture name="BRYCE right0009" x="1616" y="2103" width="718" height="795" frameX="-4" frameY="-1" frameWidth="736" frameHeight="796"/>
	<SubTexture name="BRYCE right0010" x="1616" y="2103" width="718" height="795" frameX="-4" frameY="-1" frameWidth="736" frameHeight="796"/>
	<SubTexture name="BRYCE right0011" x="1616" y="2103" width="718" height="795" frameX="-4" frameY="-1" frameWidth="736" frameHeight="796"/>
	<SubTexture name="BRYCE right0012" x="1616" y="2103" width="718" height="795" frameX="-4" frameY="-1" frameWidth="736" frameHeight="796"/>
	<SubTexture name="BRYCE right0013" x="1616" y="2103" width="718" height="795" frameX="-4" frameY="-1" frameWidth="736" frameHeight="796"/>
	<SubTexture name="BRYCE right0014" x="1616" y="2103" width="718" height="795" frameX="-4" frameY="-1" frameWidth="736" frameHeight="796"/>
	<SubTexture name="BRYCE right0015" x="1616" y="2103" width="718" height="795" frameX="-4" frameY="-1" frameWidth="736" frameHeight="796"/>
	<SubTexture name="BRYCE right0016" x="1616" y="2103" width="718" height="795" frameX="-4" frameY="-1" frameWidth="736" frameHeight="796"/>
	<SubTexture name="BRYCE right0017" x="1616" y="2103" width="718" height="795" frameX="-4" frameY="-1" frameWidth="736" frameHeight="796"/>
	<SubTexture name="BRYCE right0018" x="1616" y="2103" width="718" height="795" frameX="-4" frameY="-1" frameWidth="736" frameHeight="796"/>
	<SubTexture name="BRYCE right0019" x="1616" y="2103" width="718" height="795" frameX="-4" frameY="-1" frameWidth="736" frameHeight="796"/>
	<SubTexture name="BRYCE right0020" x="1616" y="2103" width="718" height="795" frameX="-4" frameY="-1" frameWidth="736" frameHeight="796"/>
	<SubTexture name="BRYCE right0021" x="1616" y="2103" width="718" height="795" frameX="-4" frameY="-1" frameWidth="736" frameHeight="796"/>
	<SubTexture name="BRYCE right0022" x="1616" y="2103" width="718" height="795" frameX="-4" frameY="-1" frameWidth="736" frameHeight="796"/>
	<SubTexture name="BRYCE right0023" x="1616" y="2103" width="718" height="795" frameX="-4" frameY="-1" frameWidth="736" frameHeight="796"/>
</TextureAtlas>
